shanes_scrapers/__init__.py
shanes_scrapers-0.0.2.dist-info/LICENSE
shanes_scrapers-0.0.2.dist-info/METADATA
shanes_scrapers-0.0.2.dist-info/WHEEL
shanes_scrapers-0.0.2.dist-info/top_level.txt
shanes_scrapers-0.0.2.dist-info/RECORD
