Metadata-Version: 2.1
Name: shanes-scrapers
Version: 0.0.2
Summary: Assorted scrapy scrapers (and/or APIs), some for South African sites.
Home-page: UNKNOWN
Author: Shane Matuszek
Author-email: UNKNOWN
License: UNKNOWN
Platform: UNKNOWN
Requires-Dist: scrapy
